ghon/__init__.py
ghon/api.py
ghon/cli.py
ghon-0.0.0.dist-info/METADATA
ghon-0.0.0.dist-info/WHEEL
ghon-0.0.0.dist-info/entry_points.txt
ghon-0.0.0.dist-info/RECORD
