Metadata-Version: 2.1
Name: ghon
Version: 0.0.0
Summary: TODO
Home-page: https://github.com/to/do
Author: Sean Chatman
Author-email: info@chatmangpt.com
Requires-Python: >=3.10,<4.0
Classifier: Programming Language :: Python :: 3
Classifier: Programming Language :: Python :: 3.10
Classifier: Programming Language :: Python :: 3.11
Classifier: Programming Language :: Python :: 3.12
Requires-Dist: coloredlogs (>=15.0.1)
Requires-Dist: dspygen (>=2024.4.17,<2025.0.0)
Requires-Dist: fastapi[all] (>=0.110.1)
Requires-Dist: gunicorn (>=21.2.0)
Requires-Dist: poethepoet (>=0.25.0)
Requires-Dist: typer[all] (>=0.12.0)
Requires-Dist: uvicorn[standard] (>=0.29.0)
Project-URL: Repository, https://github.com/to/do
